coverbot/__init__.py
coverbot/__main__.py
coverbot/cover.py
coverbot/deal.py
coverbot/version.py
coverbot-0.1.2.dist-info/LICENSE
coverbot-0.1.2.dist-info/WHEEL
coverbot-0.1.2.dist-info/METADATA
coverbot-0.1.2.dist-info/RECORD
